ape_utils/__init__.py
ape_utils/__version__.py
ape_utils/_cli.py
ape_utils/py.typed
ape_utils/utils.py
ape_utils-0.0.6.dist-info/METADATA
ape_utils-0.0.6.dist-info/WHEEL
ape_utils-0.0.6.dist-info/entry_points.txt
ape_utils-0.0.6.dist-info/licenses/AUTHORS.md
ape_utils-0.0.6.dist-info/licenses/LICENSE
ape_utils-0.0.6.dist-info/RECORD
