Metadata-Version: 2.3
Name: ape-utils
Version: 0.0.6
Summary: Utility plugin to expose some of the Ape's awesome features to CLI
Project-URL: Documentation, https://github.com/Aviksaikat/ape-utils#readme
Project-URL: Issues, https://github.com/Aviksaikat/ape-utils/issues
Project-URL: Source, https://github.com/Aviksaikat/ape-utils
Author-email: SAIKAT KARMAKAR <github.maturity983@passinbox.com>
License: Apache-2.0
License-File: AUTHORS.md
License-File: LICENSE
Keywords: ethereum
Classifier: Development Status :: 5 - Production/Stable
Classifier: Intended Audience :: Developers
Classifier: License :: OSI Approved :: Apache Software License
Classifier: Natural Language :: English
Classifier: Operating System :: MacOS
Classifier: Operating System :: POSIX
Classifier: Programming Language :: Python :: 3
Classifier: Programming Language :: Python :: 3.9
Classifier: Programming Language :: Python :: 3.10
Classifier: Programming Language :: Python :: 3.11
Classifier: Programming Language :: Python :: 3.12
Requires-Python: >=3.9
Requires-Dist: eth-ape>=0.8.9
Requires-Dist: ethpm-types
Requires-Dist: multicall
Requires-Dist: rich-click
